README.rst
setup.py
client/__init__.py
client/config.py
client/job_code_messages.py
client/job_dispatcher.py
client/job_executor.py
client/job_register.py
client/job_running_num.py
client/job_zk_client.py
client/singleton.py
schedulerplus_client.egg-info/PKG-INFO
schedulerplus_client.egg-info/SOURCES.txt
schedulerplus_client.egg-info/dependency_links.txt
schedulerplus_client.egg-info/requires.txt
schedulerplus_client.egg-info/top_level.txt