Metadata-Version: 1.1
Name: schedulerplus-client
Version: 0.0.16
Summary: A python schedulerplus client
Home-page: UNKNOWN
Author: lattebank
Author-email: UNKNOWN
License: MIT
Keywords: sample setuptools development
Platform: UNKNOWN
Classifier: Development Status :: 3 - Alpha
Classifier: Intended Audience :: Developers
Classifier: Topic :: Software Development :: Build Tools
Classifier: License :: OSI Approved :: MIT License
Classifier: Programming Language :: Python :: 2.7
